README.rst
setup.cfg
setup.py
espnff/__init__.py
espnff/espnff.py
espnff/utils.py
espnff.egg-info/PKG-INFO
espnff.egg-info/SOURCES.txt
espnff.egg-info/dependency_links.txt
espnff.egg-info/requires.txt
espnff.egg-info/top_level.txt