Metadata-Version: 1.1
Name: espnff
Version: 1.2.2
Summary: ESPN fantasy football API
Home-page: https://github.com/rbarton65/espnff
Author: Rich Barton
Author-email: rbart65@gmail.com
License: UNKNOWN
Platform: UNKNOWN
Classifier: Natural Language :: English
Classifier: Operating System :: OS Independent
Classifier: License :: OSI Approved :: BSD License
Classifier: Programming Language :: Python :: 3
Classifier: Topic :: Software Development :: Libraries :: Python Modules
